.hgignore
.hgtags
HISTORY.txt
MANIFEST.in
README.txt
setup.py
targetpay/__init__.py
targetpay/base.py
targetpay/ideal.py
targetpay.egg-info/PKG-INFO
targetpay.egg-info/SOURCES.txt
targetpay.egg-info/dependency_links.txt
targetpay.egg-info/not-zip-safe
targetpay.egg-info/top_level.txt