Metadata-Version: 1.0
Name: targetpay
Version: 0.3
Summary: Python interface to the TargetPay.com payment service provider
Home-page: http://www.bitbucket.org/bram/python-targetpay/
Author: Bram Duvigneau
Author-email: bram@bramd.nl
License: UNKNOWN
Keywords: targetpay payment ideal
Platform: UNKNOWN
Classifier: Development Status :: 3 - Alpha
Classifier: Intended Audience :: Developers
